{
    "related_post": {
        "ts": "2020-04-22T21:39:48.419000",
        "user": "Londan",
        "text": "i want (\"Select Game Difficulty\") to appear",
        "conversation_id": "1101",
        "index": 16
    },
    "so_post": {
        "ts": "2020-04-22T21:42:05.819000",
        "user": "Kris",
        "text": "https://stackoverflow.com/questions/20842801/howtodisplaytextinpygame",
        "conversation_id": "1101",
        "index": 20
    },
    "category": "Direct Solution Provided by Non-Asker",
    "comments": "User seems to be asking a question of how to print text with pygame.",
    "meta": {
        "start_date": "2020-04-01T00:02:12.875000",
        "end_time": null,
        "channel_name": "python-general",
        "team_domain": "Python",
        "count": 76489
    }
}