{
    "related_post": {
        "ts": "2020-08-15T22:06:36.042000",
        "user": "Benji",
        "text": "<https://stackoverflow.com/questions/25762332/howtogetallthekeyswiththesamehighestvalue>",
        "conversation_id": "1074",
        "index": 142
    },
    "so_post": {
        "ts": "2020-08-15T22:06:36.042000",
        "user": "Benji",
        "text": "<https://stackoverflow.com/questions/25762332/howtogetallthekeyswiththesamehighestvalue>",
        "conversation_id": "1074",
        "index": 142
    },
    "category": "Other",
    "comments": "ooc",
    "meta": {
        "start_date": "2020-08-01T00:00:09.346000",
        "end_time": null,
        "channel_name": "python-general",
        "team_domain": "Python",
        "count": 209359
    }
}