{
    "related_post": {
        "ts": "2020-03-26T11:05:32.829000",
        "user": "Crispin",
        "text": "anyone know how i can bson.Marshal []map[string]string",
        "conversation_id": "1422",
        "index": 4
    },
    "so_post": {
        "ts": "2020-03-26T11:11:49.903000",
        "user": "Aleah",
        "text": "@Deleted User https://stackoverflow.com/questions/47321275/ingohowtounmarshalbsonbytedataintoanarrayofstructs",
        "conversation_id": "1422",
        "index": 6
    },
    "category": "Direct Solution Provided by Non-Asker",
    "comments": "Crispin asks and Aleah provides direct SO answer",
    "meta": {
        "start_date": "2020-02-01T05:01:13.368000",
        "end_time": null,
        "channel_name": "golang",
        "team_domain": "Discord Gophers",
        "count": 72110
    }
}