{
    "related_post": {
        "ts": "2020-09-24T06:34:25.682000",
        "user": "Abdelmajid",
        "text": "@Deleted User something like dis https://stackoverflow.com/questions/46406072/howtoconvertstringtointwithoutusinglibraryfunctionsinpython O:",
        "conversation_id": "1674",
        "index": 194
    },
    "so_post": {
        "ts": "2020-09-24T06:34:25.682000",
        "user": "Abdelmajid",
        "text": "@Deleted User something like dis https://stackoverflow.com/questions/46406072/howtoconvertstringtointwithoutusinglibraryfunctionsinpython O:",
        "conversation_id": "1674",
        "index": 194
    },
    "category": "Other",
    "comments": "ooc",
    "meta": {
        "start_date": "2020-09-01T00:00:01.179000",
        "end_time": null,
        "channel_name": "python-general",
        "team_domain": "Python",
        "count": 173067
    }
}