{
    "related_post": {
        "ts": "2019-11-16T06:54:03.318000",
        "user": "Silvano",
        "text": "<https://stackoverflow.com/questions/25506281/whatareallthepossiblecalculationsthatcouldcauseananinpython>",
        "conversation_id": "571",
        "index": 9
    },
    "so_post": {
        "ts": "2019-11-16T06:54:03.318000",
        "user": "Silvano",
        "text": "<https://stackoverflow.com/questions/25506281/whatareallthepossiblecalculationsthatcouldcauseananinpython>",
        "conversation_id": "571",
        "index": 9
    },
    "category": "Other",
    "comments": "ooc",
    "meta": {
        "start_date": "2019-11-01T00:04:50.546000",
        "end_time": null,
        "channel_name": "python-general",
        "team_domain": "Python",
        "count": 33912
    }
}