{
    "related_post": {
        "ts": "2019-11-02T16:59:16.393000",
        "user": "Lazaro",
        "text": "https://stackoverflow.com/a/1060872",
        "conversation_id": "63",
        "index": 28
    },
    "so_post": {
        "ts": "2019-11-02T16:59:16.393000",
        "user": "Lazaro",
        "text": "https://stackoverflow.com/a/1060872",
        "conversation_id": "63",
        "index": 28
    },
    "category": "Other",
    "comments": "ooc",
    "meta": {
        "start_date": "2019-11-01T00:04:50.546000",
        "end_time": null,
        "channel_name": "python-general",
        "team_domain": "Python",
        "count": 33912
    }
}